[
	{
		"inputs": [
			{
				"internalType": "string",
				"name": "_name",
				"type": "string"
			},
			{
				"internalType": "string",
				"name": "_email",
				"type": "string"
			},
			{
				"internalType": "uint256",
				"name": "_dob",
				"type": "uint256"
			},
			{
				"internalType": "uint256",
				"name": "_idNumber",
				"type": "uint256"
			},
			{
				"internalType": "uint256",
				"name": "_phoneNumber",
				"type": "uint256"
			}
		],
		"name": "registerUser",
		"outputs": [],
		"stateMutability": "nonpayable",
		"type": "function"
	},
	{
		"inputs": [
			{
				"internalType": "address",
				"name": "",
				"type": "address"
			}
		],
		"name": "clients",
		"outputs": [
			{
				"internalType": "string",
				"name": "name",
				"type": "string"
			},
			{
				"internalType": "string",
				"name": "email",
				"type": "string"
			},
			{
				"internalType": "uint256",
				"name": "date_of_birth",
				"type": "uint256"
			},
			{
				"internalType": "uint256",
				"name": "idNumber",
				"type": "uint256"
			},
			{
				"internalType": "uint256",
				"name": "phoneNumber",
				"type": "uint256"
			}
		],
		"stateMutability": "view",
		"type": "function"
	},
	{
		"inputs": [],
		"name": "getUserData",
		"outputs": [
			{
				"internalType": "address[]",
				"name": "",
				"type": "address[]"
			}
		],
		"stateMutability": "view",
		"type": "function"
	},
	{
		"inputs": [
			{
				"internalType": "uint256",
				"name": "",
				"type": "uint256"
			}
		],
		"name": "usersList",
		"outputs": [
			{
				"internalType": "address",
				"name": "",
				"type": "address"
			}
		],
		"stateMutability": "view",
		"type": "function"
	}
]